cigvis/__init__.py
cigvis/colormap.py
cigvis/colors.py
cigvis/config.py
cigvis/customcmap.py
cigvis/mpl1dplot.py
cigvis/mpl2dplot.py
cigvis/mplstyle.py
cigvis/plotlyplot.py
cigvis/tools.py
cigvis/viserplot.py
cigvis/vispyplot.py
cigvis/gui/__init__.py
cigvis/gui/custom_widgets.py
cigvis/gui/gui2d/__init__.py
cigvis/gui/gui2d/control_panel.py
cigvis/gui/gui2d/mainwindow.py
cigvis/gui/gui2d/plot_canvas.py
cigvis/gui/gui3d/__init__.py
cigvis/gui/gui3d/control_panel.py
cigvis/gui/gui3d/mainwindow.py
cigvis/gui/gui3d/plot_canvas.py
cigvis/io/__init__.py
cigvis/io/fault_skin.py
cigvis/io/horiz.py
cigvis/io/las.py
cigvis/io/vds.py
cigvis/meshs/__init__.py
cigvis/meshs/indicator.py
cigvis/meshs/merge.py
cigvis/meshs/points.py
cigvis/meshs/surfaces.py
cigvis/meshs/well_logs.py
cigvis/utils/__init__.py
cigvis/utils/coord.py
cigvis/utils/maskutils.py
cigvis/utils/plotlyutils.py
cigvis/utils/surfaceutils.py
cigvis/utils/utils.py
cigvis/utils/vispyutils.py
cigvis/visernodes/__init__.py
cigvis/visernodes/meshnode.py
cigvis/visernodes/server.py
cigvis/visernodes/volume_slice.py
cigvis/visernodes/well_log.py
cigvis/vispynodes/__init__.py
cigvis/vispynodes/axis3d.py
cigvis/vispynodes/axis_aligned_image.py
cigvis/vispynodes/canvas_mixin.py
cigvis/vispynodes/colorbar.py
cigvis/vispynodes/fixed_image.py
cigvis/vispynodes/indicator.py
cigvis/vispynodes/meshnode.py
cigvis/vispynodes/vis_canvas.py
cigvis/vispynodes/volume_slices.py
cigvis/vispynodes/well_log.py
cigvis-0.2.0.dist-info/licenses/LICENSE
cigvis-0.2.0.dist-info/METADATA
cigvis-0.2.0.dist-info/WHEEL
cigvis-0.2.0.dist-info/top_level.txt
cigvis-0.2.0.dist-info/RECORD
