Metadata-Version: 2.4
Name: cigvis
Version: 0.2.0
Summary: CIGVis is a tool for geophysical data visualization
Author-email: Jintao Li <lijintaobt@gmail.com>
License: MIT
Project-URL: Homepage, https://github.com/JintaoLee-Roger/cigvis
Project-URL: documentation, https://cigvis.readthedocs.io/en/latest/
Keywords: visualization,geophysics,seismic,data,cigvis
Classifier: Programming Language :: Python :: 3
Classifier: Programming Language :: Python :: 3.8
Classifier: Programming Language :: Python :: 3.9
Classifier: Programming Language :: Python :: 3.10
Classifier: Programming Language :: Python :: 3.11
Classifier: Programming Language :: Python :: 3.12
Classifier: License :: OSI Approved :: MIT License
Classifier: Operating System :: OS Independent
Requires-Python: >=3.8
License-File: LICENSE
Requires-Dist: numpy
Requires-Dist: matplotlib
Requires-Dist: scipy
Requires-Dist: scikit-image
Provides-Extra: default
Requires-Dist: vispy; extra == "default"
Requires-Dist: PyQt5; extra == "default"
Provides-Extra: viser
Requires-Dist: viser; extra == "viser"
Provides-Extra: plotly
Requires-Dist: plotly; extra == "plotly"
Requires-Dist: pandas; extra == "plotly"
Provides-Extra: all
Requires-Dist: vispy; extra == "all"
Requires-Dist: PyQt5; extra == "all"
Requires-Dist: viser; extra == "all"
Requires-Dist: plotly; extra == "all"
Requires-Dist: pandas; extra == "all"
Dynamic: license-file
